qcportal/__init__.py
qcportal/all_inputs.py
qcportal/all_results.py
qcportal/base_models.py
qcportal/cache.py
qcportal/client.py
qcportal/client_base.py
qcportal/compare_records.py
qcportal/compression.py
qcportal/dataset_models.py
qcportal/dataset_testing_helpers.py
qcportal/exceptions.py
qcportal/generic_result.py
qcportal/manager_client.py
qcportal/metadata_models.py
qcportal/project_models.py
qcportal/record_models.py
qcportal/serialization.py
qcportal/test_cache.py
qcportal/test_dataset_models.py
qcportal/test_hashing.py
qcportal/test_metadata_models.py
qcportal/test_record_enum.py
qcportal/test_record_models.py
qcportal/test_utils.py
qcportal/utils.py
qcportal/auth/__init__.py
qcportal/auth/models.py
qcportal/external/__init__.py
qcportal/external/crystalatte.py
qcportal/external/scaffold.py
qcportal/external/test_scaffold.py
qcportal/external_files/__init__.py
qcportal/external_files/models.py
qcportal/gridoptimization/__init__.py
qcportal/gridoptimization/dataset_models.py
qcportal/gridoptimization/record_models.py
qcportal/gridoptimization/test_dataset_models.py
qcportal/gridoptimization/test_record_models.py
qcportal/internal_jobs/__init__.py
qcportal/internal_jobs/models.py
qcportal/internal_jobs/test_enum.py
qcportal/managers/__init__.py
qcportal/managers/models.py
qcportal/managers/test_manager_enum.py
qcportal/manybody/__init__.py
qcportal/manybody/dataset_models.py
qcportal/manybody/record_models.py
qcportal/manybody/test_dataset_models.py
qcportal/manybody/test_record_models.py
qcportal/molecules/__init__.py
qcportal/molecules/models.py
qcportal/molecules/test_models.py
qcportal/neb/__init__.py
qcportal/neb/dataset_models.py
qcportal/neb/record_models.py
qcportal/neb/test_dataset_models.py
qcportal/neb/test_record_models.py
qcportal/optimization/__init__.py
qcportal/optimization/dataset_models.py
qcportal/optimization/record_models.py
qcportal/optimization/test_dataset_models.py
qcportal/optimization/test_record_models.py
qcportal-0.63.dist-info/licenses/LICENSE
qcportal-0.63.dist-info/METADATA
qcportal-0.63.dist-info/WHEEL
qcportal-0.63.dist-info/top_level.txt
qcportal-0.63.dist-info/RECORD
