Metadata-Version: 2.4
Name: qcportal
Version: 0.63
Summary: A distributed compute and database platform for quantum chemistry.
Author-email: Benjamin Pritchard <qcarchive@molssi.org>
License-Expression: BSD-3-Clause
Project-URL: Homepage, https://github.com/MolSSI/QCFractal
Project-URL: Bug Tracker, https://github.com/MolSSI/QCFractal/issues
Classifier: Programming Language :: Python :: 3
Classifier: Development Status :: 4 - Beta
Classifier: Intended Audience :: Science/Research
Classifier: Operating System :: POSIX :: Linux
Classifier: Operating System :: MacOS
Requires-Python: >=3.10
License-File: LICENSE
Requires-Dist: numpy
Requires-Dist: msgpack
Requires-Dist: requests
Requires-Dist: pyyaml
Requires-Dist: pydantic
Requires-Dist: zstandard
Requires-Dist: apsw>=3.42
Requires-Dist: qcelemental<0.70a0
Requires-Dist: pint
Requires-Dist: tabulate
Requires-Dist: tqdm
Requires-Dist: pandas
Requires-Dist: pyjwt>=2.10
Requires-Dist: packaging
Requires-Dist: typing_extensions
Requires-Dist: python-dateutil
Requires-Dist: pytz
Dynamic: license-file
